seleniumwire/__init__.py
seleniumwire/__main__.py
seleniumwire/backend.py
seleniumwire/ca.crt
seleniumwire/ca.key
seleniumwire/handler.py
seleniumwire/har.py
seleniumwire/inspect.py
seleniumwire/modifier.py
seleniumwire/request.py
seleniumwire/server.py
seleniumwire/storage.py
seleniumwire/utils.py
seleniumwire/webdriver.py
seleniumwire/thirdparty/__init__.py
seleniumwire/thirdparty/mitmproxy/__init__.py
seleniumwire/thirdparty/mitmproxy/addonmanager.py
seleniumwire/thirdparty/mitmproxy/certs.py
seleniumwire/thirdparty/mitmproxy/command.py
seleniumwire/thirdparty/mitmproxy/command_lexer.py
seleniumwire/thirdparty/mitmproxy/connections.py
seleniumwire/thirdparty/mitmproxy/controller.py
seleniumwire/thirdparty/mitmproxy/ctx.py
seleniumwire/thirdparty/mitmproxy/eventsequence.py
seleniumwire/thirdparty/mitmproxy/exceptions.py
seleniumwire/thirdparty/mitmproxy/flow.py
seleniumwire/thirdparty/mitmproxy/flowfilter.py
seleniumwire/thirdparty/mitmproxy/http.py
seleniumwire/thirdparty/mitmproxy/log.py
seleniumwire/thirdparty/mitmproxy/master.py
seleniumwire/thirdparty/mitmproxy/options.py
seleniumwire/thirdparty/mitmproxy/optmanager.py
seleniumwire/thirdparty/mitmproxy/stateobject.py
seleniumwire/thirdparty/mitmproxy/tcp.py
seleniumwire/thirdparty/mitmproxy/types.py
seleniumwire/thirdparty/mitmproxy/version.py
seleniumwire/thirdparty/mitmproxy/websocket.py
seleniumwire/thirdparty/mitmproxy/addons/__init__.py
seleniumwire/thirdparty/mitmproxy/addons/core.py
seleniumwire/thirdparty/mitmproxy/addons/streambodies.py
seleniumwire/thirdparty/mitmproxy/addons/upstream_auth.py
seleniumwire/thirdparty/mitmproxy/contrib/__init__.py
seleniumwire/thirdparty/mitmproxy/contrib/kaitaistruct/__init__.py
seleniumwire/thirdparty/mitmproxy/contrib/kaitaistruct/exif.py
seleniumwire/thirdparty/mitmproxy/contrib/kaitaistruct/exif_be.py
seleniumwire/thirdparty/mitmproxy/contrib/kaitaistruct/exif_le.py
seleniumwire/thirdparty/mitmproxy/contrib/kaitaistruct/gif.py
selenium_wire-5.0.0.dist-info/AUTHORS.rst
selenium_wire-5.0.0.dist-info/LICENSE
selenium_wire-5.0.0.dist-info/METADATA
selenium_wire-5.0.0.dist-info/NOTICES
selenium_wire-5.0.0.dist-info/WHEEL
selenium_wire-5.0.0.dist-info/top_level.txt
selenium_wire-5.0.0.dist-info/RECORD
