Metadata-Version: 2.1
Name: selenium-wire
Version: 5.0.0
Summary: Extends Selenium to give you the ability to inspect requests made by the browser.
Home-page: https://github.com/wkeeling/selenium-wire
Author: Will Keeling
Author-email: will@zifferent.com
License: MIT
Keywords: selenium-wire
Platform: UNKNOWN
Classifier: Development Status :: 4 - Beta
Classifier: Intended Audience :: Developers
Classifier: License :: OSI Approved :: MIT License
Classifier: Natural Language :: English
Classifier: Operating System :: MacOS
Classifier: Operating System :: POSIX
Classifier: Operating System :: Microsoft :: Windows
Classifier: Programming Language :: Python :: 3.6
Classifier: Programming Language :: Python :: 3.7
Classifier: Programming Language :: Python :: 3.8
Classifier: Programming Language :: Python :: 3.9
Classifier: Programming Language :: Python :: 3.10
Requires-Python: >=3.6
Provides-Extra: dev
